{
    "fields": [
        {
            "id": "addr1"
        },
        {
            "id": "areacode"
        },
        {
            "id": "cat1"
        },
        {
            "id": "cat2"
        },
        {
            "id": "cat3"
        },
        {
            "id": "contentid"
        },
        {
            "id": "contenttypeid"
        },
        {
            "id": "createdtime"
        },
        {
            "id": "firstimage"
        },
        {
            "id": "firstimage2"
        },
        {
            "id": "mapx"
        },
        {
            "id": "mapy"
        },
        {
            "id": "mlevel"
        },
        {
            "id": "modifiedtime"
        },
        {
            "id": "readcount"
        },
        {
            "id": "sigungucode"
        },
        {
            "id": "tel"
        },
        {
            "id": "title"
        }
    ],
    "records": [
        {
            "contentid": "1842315",
            "firstimage": "http://tong.visitkorea.or.kr/cms/resource/37/2567837_image2_1.jpg",
            "tel": "+82-55-322-4735",
            "title": "Gimhae Hanok Experience Hall ",
            "addr1": "40, Garak-ro 93beon-gil, Gimhae-si, Gyeongsangnam-do",
            "information": "The Gimhae Hanok Experience Hall built by Gimhae city and run by Gimhae Culture Foundation offers ondol-style rooms for the visitors."
        },
        {
            "contentid": "497140",
            "firstimage": "http://tong.visitkorea.or.kr/cms/resource/33/1610933_image2_1.jpg",
            "tel": "+82-61-382-3832",
            "title": "Hanoka Pension",
            "addr1": "88-9, Doldam-gil Changpyeong-myeon, Damyang-gun, Jeollanam-do ",
            "information": "Hanok Pension is an old traditional Korean house located in Samjinae Village, Changpyeong-myeon, Damyang-gun, the first village in Asia to be listed as a 'Slow Village.'"
        },
        {
            "contentid": "497630",
            "firstimage": "http://tong.visitkorea.or.kr/cms/resource/63/2580363_image2_1.jpg",
            "tel": "+82-10-3451-5769",
            "title": "Gongju Traditional Korean Village",
            "addr1": "12, Gwangwangdanji-gil, Gongju-si, Chungcheongnam-do ",
            "information": "Gongju Traditional Korean Village is located between the Tomb of King Muryeong and the Gongju National Museum in Gongju, which is often referred to as ‘a roofless museum’ due to the preponderance of historic sites. Opened as a hanok stay on a 30,000m2 site in 2010, the Village, which is entirely composed of tiled-roof hanok houses and thatched-roof houses, offers attractive hanok accommodation that combines traditional and modern styles, and has rooms equipped with a Korean floor heating system (gudeul), as well as a pavilion. It also runs diverse experience programs relating to the history of the Baekje Kingdom. "
        },
        {
            "contentid": "1319418",
            "firstimage": "",
            "tel": "",
            "title": "",
            "addr1": "",
            "information": ""
        },
        {
            "contentid": "1352687",
            "firstimage": "",
            "tel": "",
            "title": "",
            "addr1": "",
            "information": ""
        },
        {
            "contentid": "1272243",
            "firstimage": "",
            "tel": "",
            "title": "",
            "addr1": "",
            "information": ""
        },
        {
            "contentid": "1220876",
            "firstimage": "",
            "tel": "",
            "title": "",
            "addr1": "",
            "information": ""
        },
        {
            "contentid": "497249",
            "firstimage": "",
            "tel": "",
            "title": "",
            "addr1": "",
            "information": ""
        },
        {
            "contentid": "496956",
            "firstimage": "",
            "tel": "",
            "title": "",
            "addr1": "",
            "information": ""
        },
        {
            "contentid": "1011120",
            "firstimage": "",
            "tel": "",
            "title": "",
            "addr1": "",
            "information": ""
        }
    ]
}
